{
  "actionType" : "NEWT",
  "allocationIndicator" : "UNAL",
  "blockTradeElectionIndicator" : false,
  "buyerIdentifier" : "DUMMYLEI123456789002",
  "callAmount" : 500000000,
  "callCurrency" : "EUR",
  "cftcGuidebook" : {
    "assetClass" : "Credit",
    "largeNotionalOffFacilitySwapElectionIndicator" : false,
    "mandatoryClearingIndicator" : false,
    "maturityDateOfTheUnderlier" : "2024-12-20",
    "messageType" : "Trade State",
    "optionStyle" : "EURO",
    "optionType" : "CALL",
    "physicalCommodityIndicator" : false,
    "sefOrDcmAnonymousExecutionIndicator" : false,
    "sefOrDcmIndicator" : false,
    "settlementType" : "CASH"
  },
  "cleared" : "N",
  "counterparty1" : "DUMMYLEI123456789002",
  "counterparty1FederalEntityIndicator" : false,
  "counterparty1FinancialEntityIndicator" : false,
  "counterparty2" : "DUMMYLEI123456789001",
  "counterparty2FederalEntityIndicator" : false,
  "counterparty2FinancialEntityIndicator" : false,
  "counterparty2IdentifierSource" : "LEID",
  "customBasketIndicator" : false,
  "effectiveDate" : "2020-02-27",
  "eventIdentifier" : "DTDUnapproved11370799001DFCFTCRiskNewNewCre",
  "eventTimestamp" : "2022-02-11T07:48:32Z",
  "eventType" : "TRAD",
  "executionTimestamp" : "2022-02-11T07:48:14Z",
  "expirationDate" : "2020-03-18",
  "finalContractualSettlementDate" : "2024-12-20",
  "firstExerciseDate" : "2020-03-18",
  "fixedRateDayCountConventionLeg1" : "A004",
  "fixedRatePaymentFrequencyPeriodLeg1" : "MNTH",
  "fixedRatePaymentFrequencyPeriodMultiplierLeg1" : 3,
  "initialMarginCollateralPortfolioCode" : "Not Modelled",
  "jurisdiction" : "CFTC",
  "newSDRIdentifier" : "Not Modelled",
  "nonReportable" : {
    "buyerIdentifierFormat" : "Lei",
    "counterparty1Format" : "Lei",
    "counterparty2Format" : "Lei",
    "payerIdentifierLeg1Format" : "Lei",
    "payerIdentifierLeg2Format" : "Lei",
    "receiverIdentifierLeg1Format" : "Lei",
    "receiverIdentifierLeg2Format" : "Lei",
    "sellerIdentifierFormat" : "Lei"
  },
  "nonStandardizedTermIndicator" : false,
  "notionalAmountLeg1" : 500000000,
  "notionalCurrencyLeg1" : "EUR",
  "optionPremiumAmount" : 0,
  "optionPremiumCurrency" : "EUR",
  "optionPremiumPaymentDate" : "2020-02-27",
  "packageIndicator" : false,
  "postPricedSwapIndicator" : false,
  "primeBrokerageTransactionIndicator" : false,
  "putAmount" : 500000000,
  "putCurrency" : "EUR",
  "reportingTimestamp" : "2024-04-29T00:00:00Z",
  "sellerIdentifier" : "DUMMYLEI123456789001",
  "settlementCurrencyLeg1" : "CNY",
  "settlementLocationLeg1" : "HK",
  "strikePrice" : 0.0100000000000,
  "strikePriceNotation" : "3",
  "submitterIdentifier" : "DUMMYLEI123456789002",
  "uniqueTransactionIdentifier" : "CREDITSWAPTIONITRA02",
  "variationMarginCollateralPortfolioCode" : "Not Modelled"
}